<annotation>
	<folder></folder>
	<filename>20_png.rf.ea09e631c5aadb3dd91c3bbf7022dc53.jpg</filename>
	<path>20_png.rf.ea09e631c5aadb3dd91c3bbf7022dc53.jpg</path>
	<source>
		<database>roboflow.com</database>
	</source>
	<size>
		<width>640</width>
		<height>640</height>
		<depth>3</depth>
	</size>
	<segmented>0</segmented>
	<object>
		<name>trees</name>
		<pose>Unspecified</pose>
		<truncated>0</truncated>
		<difficult>0</difficult>
		<occluded>0</occluded>
		<bndbox>
			<xmin>1</xmin>
			<xmax>87</xmax>
			<ymin>1</ymin>
			<ymax>120</ymax>
		</bndbox>
		<polygon>
			<x1>0</x1>
			<y1>0</y1>
			<x2>0</x2>
			<y2>61.592047</y2>
			<x3>10.453608</x3>
			<y3>66.072165</y3>
			<x4>38.494845</x4>
			<y4>117.206186</y4>
			<x5>59.938144</x5>
			<y5>118.85567</y5>
			<x6>86.329897</x6>
			<y6>95.762887</y6>
			<x7>86.329897</x7>
			<y7>26.484536</y7>
			<x8>82.271782</x8>
			<y8>0</y8>
			<x9>0</x9>
			<y9>0</y9>
		</polygon>
	</object>
	<object>
		<name>trees</name>
		<pose>Unspecified</pose>
		<truncated>0</truncated>
		<difficult>0</difficult>
		<occluded>0</occluded>
		<bndbox>
			<xmin>196</xmin>
			<xmax>327</xmax>
			<ymin>227</ymin>
			<ymax>333</ymax>
		</bndbox>
		<polygon>
			<x1>326</x1>
			<y1>332</y1>
			<x2>326</x2>
			<y2>231.088097</y2>
			<x3>289.216495</x3>
			<y3>226.072165</y3>
			<x4>239.731959</x4>
			<y4>232.670103</y4>
			<x5>221.587629</x5>
			<y5>247.515464</y5>
			<x6>195.195876</x6>
			<y6>280.505155</y6>
			<x7>196.845361</x7>
			<y7>295.350515</y7>
			<x8>277.670103</x8>
			<y8>293.701031</y8>
			<x9>213.340206</x9>
			<y9>308.546392</y9>
			<x10>205.092784</x10>
			<y10>326.690722</y10>
			<x11>207.506092</x11>
			<y11>332</y11>
			<x12>326</x12>
			<y12>332</y12>
		</polygon>
	</object>
	<object>
		<name>trees</name>
		<pose>Unspecified</pose>
		<truncated>0</truncated>
		<difficult>0</difficult>
		<occluded>0</occluded>
		<bndbox>
			<xmin>1</xmin>
			<xmax>140</xmax>
			<ymin>377</ymin>
			<ymax>549</ymax>
		</bndbox>
		<polygon>
			<x1>0</x1>
			<y1>547.876289</y1>
			<x2>122.618557</x2>
			<y2>505.92783499999996</y2>
			<x3>125.917526</x3>
			<y3>469.639175</y3>
			<x4>139.113402</x4>
			<y4>459.74226799999997</y4>
			<x5>87.979381</x5>
			<y5>375.618557</y5>
			<x6>22</x6>
			<y6>375.618557</y6>
			<x7>0</x7>
			<y7>390.521783</y7>
			<x8>0</x8>
			<y8>547.876289</y8>
		</polygon>
	</object>
	<object>
		<name>trees</name>
		<pose>Unspecified</pose>
		<truncated>0</truncated>
		<difficult>0</difficult>
		<occluded>0</occluded>
		<bndbox>
			<xmin>467</xmin>
			<xmax>515</xmax>
			<ymin>347</ymin>
			<ymax>424</ymax>
		</bndbox>
		<polygon>
			<x1>511.13551</x1>
			<y1>371.874667</y1>
			<x2>511.13551</x2>
			<y2>367.4928</y2>
			<x3>507.940408</x3>
			<y3>363.279467</y3>
			<x4>507.940408</x4>
			<y4>359.066133</y4>
			<x5>504.745306</x5>
			<y5>354.684267</y5>
			<x6>504.745306</x6>
			<y6>350.470933</y6>
			<x7>501.38204099999996</x7>
			<y7>346.2576</y7>
			<x8>478.511837</x8>
			<y8>346.2576</y8>
			<x9>475.316735</x9>
			<y9>350.470933</y9>
			<x10>471.95346900000004</x10>
			<y10>350.470933</y10>
			<x11>465.563265</x11>
			<y11>359.066133</y11>
			<x12>465.563265</x12>
			<y12>397.3232</y12>
			<x13>468.758367</x13>
			<y13>401.705067</y13>
			<x14>468.758367</x14>
			<y14>405.9184</y14>
			<x15>481.87510199999997</x15>
			<y15>422.940267</y15>
			<x16>514.498776</x16>
			<y16>422.940267</y16>
			<x17>514.498776</x17>
			<y17>376.088</y17>
			<x18>511.13551</x18>
			<y18>371.874667</y18>
		</polygon>
	</object>
	<object>
		<name>trees</name>
		<pose>Unspecified</pose>
		<truncated>0</truncated>
		<difficult>0</difficult>
		<occluded>0</occluded>
		<bndbox>
			<xmin>375</xmin>
			<xmax>568</xmax>
			<ymin>343</ymin>
			<ymax>535</ymax>
		</bndbox>
		<polygon>
			<x1>383.835918</x1>
			<y1>461.365867</y1>
			<x2>390.39428599999997</x2>
			<y2>469.961067</y2>
			<x3>390.39428599999997</x3>
			<y3>474.1744</y3>
			<x4>396.952653</x4>
			<y4>482.76959999999997</y4>
			<x5>396.952653</x5>
			<y5>486.982933</y5>
			<x6>406.706122</x6>
			<y6>499.791467</y6>
			<x7>406.706122</x7>
			<y7>504.0048</y7>
			<x8>416.459592</x8>
			<y8>516.8133330000001</y8>
			<x9>423.017959</x9>
			<y9>516.8133330000001</y9>
			<x10>426.381224</x10>
			<y10>521.1952</y10>
			<x11>432.771429</x11>
			<y11>521.1952</y11>
			<x12>436.13469399999997</x12>
			<y12>525.408533</y12>
			<x13>445.888163</x13>
			<y13>525.408533</y13>
			<x14>449.083265</x14>
			<y14>529.6218670000001</y14>
			<x15>452.446531</x15>
			<y15>529.6218670000001</y15>
			<x16>455.641633</x16>
			<y16>534.003733</y16>
			<x17>501.38204099999996</x17>
			<y17>534.003733</y17>
			<x18>504.745306</x18>
			<y18>529.6218670000001</y18>
			<x19>527.447347</x19>
			<y19>529.6218670000001</y19>
			<x20>530.810612</x20>
			<y20>525.408533</y20>
			<x21>534.005714</x21>
			<y21>525.408533</y21>
			<x22>556.875918</x22>
			<y22>495.578133</y22>
			<x23>556.875918</x23>
			<y23>486.982933</y23>
			<x24>560.239184</x24>
			<y24>482.76959999999997</y24>
			<x25>560.239184</x25>
			<y25>478.387733</y25>
			<x26>563.4342859999999</x26>
			<y26>474.1744</y26>
			<x27>563.4342859999999</x27>
			<y27>465.74773300000004</y27>
			<x28>566.797551</x28>
			<y28>461.365867</y28>
			<x29>566.797551</x29>
			<y29>444.344</y29>
			<x30>556.875918</x30>
			<y30>431.535467</y30>
			<x31>547.122449</x31>
			<y31>431.535467</y31>
			<x32>543.927347</x32>
			<y32>435.7488</y32>
			<x33>537.36898</x33>
			<y33>435.7488</y33>
			<x34>534.005714</x34>
			<y34>440.130667</y34>
			<x35>530.810612</x35>
			<y35>440.130667</y35>
			<x36>527.447347</x36>
			<y36>444.344</y36>
			<x37>517.693878</x37>
			<y37>444.344</y37>
			<x38>514.498776</x38>
			<y38>448.55733299999997</y38>
			<x39>491.62857099999997</x39>
			<y39>448.55733299999997</y39>
			<x40>488.265306</x40>
			<y40>444.344</y40>
			<x41>481.87510199999997</x41>
			<y41>444.344</y41>
			<x42>475.316735</x42>
			<y42>435.7488</y42>
			<x43>468.758367</x43>
			<y43>435.7488</y43>
			<x44>462.2</x44>
			<y44>427.322133</y44>
			<x45>459.004898</x45>
			<y45>427.322133</y45>
			<x46>452.446531</x46>
			<y46>418.72693300000003</y46>
			<x47>449.083265</x47>
			<y47>418.72693300000003</y47>
			<x48>442.693061</x48>
			<y48>410.131733</y48>
			<x49>439.329796</x49>
			<y49>410.131733</y49>
			<x50>426.381224</x50>
			<y50>393.109867</y50>
			<x51>426.381224</x51>
			<y51>388.896533</y51>
			<x52>419.822857</x52>
			<y52>380.301333</y52>
			<x53>419.822857</x53>
			<y53>367.4928</y53>
			<x54>416.459592</x54>
			<y54>363.279467</y54>
			<x55>416.459592</x55>
			<y55>341.875733</y55>
			<x56>390.39428599999997</x56>
			<y56>341.875733</y56>
			<x57>377.277551</x57>
			<y57>359.066133</y57>
			<x58>377.277551</x58>
			<y58>363.279467</y58>
			<x59>374.082449</x59>
			<y59>367.4928</y59>
			<x60>374.082449</x60>
			<y60>418.72693300000003</y60>
			<x61>377.277551</x61>
			<y61>422.940267</y61>
			<x62>377.277551</x62>
			<y62>440.130667</y62>
			<x63>380.640816</x63>
			<y63>444.344</y63>
			<x64>380.640816</x64>
			<y64>452.9392</y64>
			<x65>383.835918</x65>
			<y65>457.152533</y65>
			<x66>383.835918</x66>
			<y66>461.365867</y66>
		</polygon>
	</object>
</annotation>
